vectorspace/chunking.py
vectorspace/core.py
vectorspace/http_server.py
vectorspace/logger.py
vectorspace/mcp_server.py
python_vectorspace-0.0.7.dist-info/METADATA
python_vectorspace-0.0.7.dist-info/WHEEL
python_vectorspace-0.0.7.dist-info/entry_points.txt
python_vectorspace-0.0.7.dist-info/top_level.txt
python_vectorspace-0.0.7.dist-info/RECORD
