Metadata-Version: 2.4
Name: python-vectorspace
Version: 0.0.7
Summary: Directory file watcher for automatically creating and querying vector embeddings.
Author-email: deathbeam <slusnucky@gmail.com>
Project-URL: Homepage, https://github.com/deathbeam/vectorspace
Project-URL: Issues, https://github.com/deathbeam/vectorspace/issues
Requires-Python: >=3.12
Requires-Dist: chromadb>=1.0.16
Requires-Dist: fastapi>=0.115.11
Requires-Dist: httpx>=0.28.1
Requires-Dist: mcp[cli]>=1.13.0
Requires-Dist: pygments>=2.19.1
Requires-Dist: tree-sitter>=0.25.1
Requires-Dist: tree-sitter-language-pack>=0.9.0
Requires-Dist: watchdog>=6.0.0
